segmentation_utils/ImagePreprocessor.py
segmentation_utils/__init__.py
segmentation_utils/flowreader.py
transform_utils/__init__.py
transform_utils/image_cutting.py
transform_utils/image_loading.py
transform_utils/image_stats.py
utilities/__init__.py
utilities/segmentation_utils/ImagePreprocessor.py
utilities/segmentation_utils/__init__.py
utilities/segmentation_utils/constants.py
utilities/segmentation_utils/flowreader.py
utilities/segmentation_utils/reading_strategies.py
utilities/segmentation_utils/tempCodeRunnerFile.py
utilities/transform_utils/__init__.py
utilities/transform_utils/image_cutting.py
utilities/transform_utils/image_loading.py
utilities/transform_utils/image_stats.py
guorbit_utils-0.1.0.dist-info/LICENSE
guorbit_utils-0.1.0.dist-info/METADATA
guorbit_utils-0.1.0.dist-info/WHEEL
guorbit_utils-0.1.0.dist-info/top_level.txt
guorbit_utils-0.1.0.dist-info/RECORD
