Metadata-Version: 2.1
Name: guorbit-utils
Version: 0.1.0
Summary: A package containing utilities for GU Orbit Software
Home-page: 
Author: GU Orbit Software Team
Author-email: 
License: MIT
Classifier: Programming Language :: Python :: 3.10
Classifier: License :: OSI Approved :: MIT License
Classifier: Operating System :: OS Independent
Requires-Python: >=3.10
License-File: LICENSE
Requires-Dist: numpy (>=1.24.0)
Requires-Dist: rasterio (>=1.3.6)
Requires-Dist: Pillow (>=9.4.0)
Requires-Dist: tensorflow (>=2.10)
Provides-Extra: dev
Requires-Dist: pytest (>=7.2.2) ; extra == 'dev'
Requires-Dist: pytest-cov (>=4.0.0) ; extra == 'dev'
Requires-Dist: twine (>=4.0.0) ; extra == 'dev'
